xy_django_serializer/__init__.py
xy_django_serializer/serializers.py
xy_django_serializer-1.0.0.dist-info/LICENSE
xy_django_serializer-1.0.0.dist-info/METADATA
xy_django_serializer-1.0.0.dist-info/WHEEL
xy_django_serializer-1.0.0.dist-info/top_level.txt
xy_django_serializer-1.0.0.dist-info/RECORD
