Metadata-Version: 2.1
Name: xy_django_serializer
Version: 1.0.0
Summary: 基于djangorestframework的serializer解析基类, 封装了常用功能, 方便快速开发.
Author-email: 余洋 <yuyangit.0515@qq.com>
Classifier: Programming Language :: Python :: 3
Requires-Python: >=3.11.3
License-File: LICENSE
Requires-Dist: djangorestframework
